spinqit_mcp_tools/__init__.py
spinqit_mcp_tools/qasm_submitter.py
spinqit_mcp_tools/backend/__init__.py
spinqit_mcp_tools/backend/backend.py
spinqit_mcp_tools/backend/backend_util.py
spinqit_mcp_tools/backend/qasm_backend.py
spinqit_mcp_tools/backend/spinq_cloud_backend.py
spinqit_mcp_tools/backend/client/__init__.py
spinqit_mcp_tools/backend/client/spinq_cloud_client.py
spinqit_mcp_tools/backend/client/spinq_session.py
spinqit_mcp_tools/backend/layout/__init__.py
spinqit_mcp_tools/backend/layout/layout.py
spinqit_mcp_tools/backend/layout/layout_util.py
spinqit_mcp_tools/backend/layout/physical_layout.py
spinqit_mcp_tools/backend/layout/routing_layout.py
spinqit_mcp_tools/backend/layout/sven_swap_mapper.py
spinqit_mcp_tools/compiler/__init__.py
spinqit_mcp_tools/compiler/compiler.py
spinqit_mcp_tools/compiler/ir.py
spinqit_mcp_tools/compiler/qasm_compiler.py
spinqit_mcp_tools/compiler/qasm/Qasm2ErrorListener.py
spinqit_mcp_tools/compiler/qasm/Qasm2EventListener.py
spinqit_mcp_tools/compiler/qasm/Qasm2Lexer.py
spinqit_mcp_tools/compiler/qasm/Qasm2Listener.py
spinqit_mcp_tools/compiler/qasm/Qasm2Parser.py
spinqit_mcp_tools/compiler/qasm/__init__.py
spinqit_mcp_tools/compiler/qasm/grammar/__init__.py
spinqit_mcp_tools/compiler/qasm/include/__init__.py
spinqit_mcp_tools/compiler/qasm/include/qelib1.inc
spinqit_mcp_tools/compiler/translator/__init__.py
spinqit_mcp_tools/compiler/translator/gate_converter.py
spinqit_mcp_tools/compiler/translator/qiskit_to_spinq.py
spinqit_mcp_tools/model/Ising_gate.py
spinqit_mcp_tools/model/__init__.py
spinqit_mcp_tools/model/basic_gate.py
spinqit_mcp_tools/model/circuit.py
spinqit_mcp_tools/model/controlled_gate.py
spinqit_mcp_tools/model/controlled_gate_decomposer.py
spinqit_mcp_tools/model/exceptions.py
spinqit_mcp_tools/model/gates.py
spinqit_mcp_tools/model/instruction.py
spinqit_mcp_tools/model/inverse_builder.py
spinqit_mcp_tools/model/matrix_gate.py
spinqit_mcp_tools/model/multi_control_phase_gate.py
spinqit_mcp_tools-0.0.1.dist-info/METADATA
spinqit_mcp_tools-0.0.1.dist-info/WHEEL
spinqit_mcp_tools-0.0.1.dist-info/entry_points.txt
spinqit_mcp_tools-0.0.1.dist-info/top_level.txt
spinqit_mcp_tools-0.0.1.dist-info/RECORD
