Metadata-Version: 2.1
Name: spinqit-mcp-tools
Version: 0.0.1
Summary: The MCP server for SpinQ Cloud.
Home-page: https://github.com/SpinQTech/spinqit_mcp_tools
Author: SpinQ
Author-email: spinqit@spinq.cn
Classifier: Programming Language :: Python :: 3
Classifier: License :: OSI Approved :: MIT License
Classifier: Operating System :: OS Independent
Requires-Python: >=3.10
Requires-Dist: annotated-types (==0.7.0)
Requires-Dist: antlr4-python3-runtime (==4.9.2)
Requires-Dist: anyio (==4.9.0)
Requires-Dist: autograd (==1.8.0)
Requires-Dist: autoray (==0.7.1)
Requires-Dist: blinker (==1.9.0)
Requires-Dist: certifi (==2025.4.26)
Requires-Dist: charset-normalizer (==3.4.2)
Requires-Dist: click (==8.2.0)
Requires-Dist: flask (==3.1.1)
Requires-Dist: h11 (==0.16.0)
Requires-Dist: httpcore (==1.0.9)
Requires-Dist: httpx (==0.28.1)
Requires-Dist: httpx-sse (==0.4.0)
Requires-Dist: idna (==3.10)
Requires-Dist: igraph (==0.11.8)
Requires-Dist: itsdangerous (==2.2.0)
Requires-Dist: jinja2 (==3.1.6)
Requires-Dist: markupsafe (==3.0.2)
Requires-Dist: mcp (==1.8.1)
Requires-Dist: numpy (<2.0,>=1.26.0)
Requires-Dist: pycryptodome (==3.22.0)
Requires-Dist: pydantic (==2.11.4)
Requires-Dist: pydantic-core (==2.33.2)
Requires-Dist: pydantic-settings (==2.9.1)
Requires-Dist: python-constraint (==1.4.0)
Requires-Dist: python-dotenv (==1.1.0)
Requires-Dist: python-multipart (==0.0.20)
Requires-Dist: requests (==2.32.3)
Requires-Dist: scipy (<1.14.0,>=1.7.0)
Requires-Dist: sniffio (==1.3.1)
Requires-Dist: sse-starlette (==2.3.5)
Requires-Dist: starlette (==0.46.2)
Requires-Dist: texttable (==1.7.0)
Requires-Dist: typing-extensions (==4.13.2)
Requires-Dist: typing-inspection (==0.4.0)
Requires-Dist: urllib3 (==2.4.0)
Requires-Dist: uvicorn (==0.34.2)
Requires-Dist: werkzeug (==3.1.3)
